pythonicforbert/__init__.py
pythonicforbert/correct_train.py
pythonicforbert/example.py
pythonicforbert/functions.py
pythonicforbert/get_model.py
pythonicforbert/loader_pretrain_weights.py
pythonicforbert/tokenization.py
pythonicforbert/train_example.py
pythonicforbert/bert/__init__.py
pythonicforbert/bert/bert.py
pythonicforbert/bert/loader_bert.py
pythonicforbert/longformer/__init__.py
pythonicforbert/longformer/load_longformer.py
pythonicforbert/longformer/loader_longformer.py
pythonicforbert/longformer/longformer.py
pythonicforbert/nezha/__init__.py
pythonicforbert/nezha/loader_nezha.py
pythonicforbert/nezha/nezha.py
pythonicforbert/roberta/__init__.py
pythonicforbert/roberta/loader_roberta.py
pythonicforbert/roberta/roberta.py
pythonicforbert-1.0.17.dist-info/METADATA
pythonicforbert-1.0.17.dist-info/WHEEL
pythonicforbert-1.0.17.dist-info/top_level.txt
pythonicforbert-1.0.17.dist-info/RECORD
