Metadata-Version: 2.1
Name: pythonicforbert
Version: 1.0.17
Summary: a package for your bert using
Home-page: https://github.com/boss2020/pytorch-transformer
Author: xiaoguzai
Author-email: 474551240@qq.com
License: Apache License 2.0
Download-URL: https://github.com/boss2020/pytorch-transformer/master.zip
Platform: UNKNOWN
Requires-Dist: torch (>=1.5.0)
